napalm_mos/__init__.py
napalm_mos/constants.py
napalm_mos/mos.py
napalm_mos/utils/__init__.py
napalm_mos-5.1.0.dist-info/AUTHORS
napalm_mos-5.1.0.dist-info/LICENSE
napalm_mos-5.1.0.dist-info/METADATA
napalm_mos-5.1.0.dist-info/WHEEL
napalm_mos-5.1.0.dist-info/top_level.txt
napalm_mos-5.1.0.dist-info/RECORD
