Metadata-Version: 2.1
Name: napalm-mos
Version: 5.1.0
Summary: Network Automation and Programmability Abstraction Layer with Multivendor support
Home-page: https://github.com/napalm-automation-community/napalm-mos
Author: Benny Holmgren, Brandon Ewing
Author-email: benny@holmgren.id.au, brandon.ewing@warningg.com
License: UNKNOWN
Platform: UNKNOWN
Classifier: Topic :: Utilities
Classifier: Programming Language :: Python
Classifier: Operating System :: POSIX :: Linux
Classifier: Operating System :: MacOS
Requires-Python: >=3.9
License-File: LICENSE
License-File: AUTHORS
Requires-Dist: napalm>=5.1.0
Requires-Dist: packaging>=25.0
